wayback/__init__.py
wayback/_client.py
wayback/_models.py
wayback/_utils.py
wayback/_version.py
wayback/exceptions.py
wayback/tests/__init__.py
wayback/tests/conftest.py
wayback/tests/support.py
wayback/tests/test_client.py
wayback/tests/test_utils.py
wayback-0.4.5.dist-info/LICENSE
wayback-0.4.5.dist-info/METADATA
wayback-0.4.5.dist-info/WHEEL
wayback-0.4.5.dist-info/entry_points.txt
wayback-0.4.5.dist-info/top_level.txt
wayback-0.4.5.dist-info/RECORD
