Metadata-Version: 2.1
Name: wayback
Version: 0.4.5
Summary: Python API to Internet Archive Wayback Machine
Home-page: https://github.com/edgi-govdata-archiving/wayback
Author: Environmental Data Governance Initiative
Author-email: EnviroDGI@protonmail.com
License: BSD (3-clause)
Project-URL: Documentation, https://wayback.readthedocs.io/en/stable/
Project-URL: Changelog, https://wayback.readthedocs.io/en/stable/release-history.html
Project-URL: Source code, https://github.com/edgi-govdata-archiving/wayback
Project-URL: Issues, https://github.com/edgi-govdata-archiving/wayback/issues
Platform: UNKNOWN
Classifier: Development Status :: 3 - Alpha
Classifier: Natural Language :: English
Classifier: Programming Language :: Python :: 3
Requires-Python: >=3.6
Provides-Extra: dev
Provides-Extra: docs
Provides-Extra: test
License-File: LICENSE
